{
  "skillMetadata":{
    "sections":[
      {
        "name": "Sound Options",
        "fields": [
          {
              "name": "sound",
              "type": "checkbox",
              "label": "activate acustic note",
              "value": "True"
          },
          {
            "name": "autoplay",
            "type": "checkbox",
            "label": "(autoplay) append note to request",
            "value": "True"
          },          
          {
              "name": "repetition",
              "type": "number",
              "label": "duration of repetition in minutes",
              "value": 60
          }
        ]
      }
    ]
  }
}